{"items":{"serializeList":[{"name":"hay","nr":2675432277.0},{"name":"wood","nr":33606597975.0},{"name":"carrot","nr":4410896514.0},{"name":"pumpkin","nr":431103701.0},{"name":"cactus","nr":1017022872.0},{"name":"bone","nr":40427257.0},{"name":"weird_substance","nr":1748624556.0},{"name":"gold","nr":120465204.0},{"name":"water","nr":16560764.0},{"name":"fertilizer","nr":529038.0},{"name":"power","nr":256076.20149987669}]},"dockedFiles":[],"minimizedFiles":["basic_plant_column","cactus_brick_lb","cactus_farmer","cactus_farmer_lb","cactus_lb","cactus_section","cactus_single_lb","cactus_spam_lb","carrot_farmer_achiev","carrot_poly_farmer","column_farmer","common","dinosaur_farmer","dinosaur_farmer_lb","dinosaur_section","dumbflower_section","entity_item_mapping","f0","f1","f2","f3","flip_achieve","hay_farmer_achieve","hay_poly_farmer","leaderboard","main","maze_calc_farmer","maze_farmer","maze_farmer_lb","maze_fill","maze_full_rand","maze_multi_a_star","maze_multi_dfs","maze_multi_reuse","maze_pre_path","maze_reuse_analysis","maze_reuse_section","maze_section","maze_section_a_star","old_code","point","pumpkin_farmer_lb","pumpkin_section","rect","save_state","suggester","sunflower_column","sunflower_farmer","sunflower_farmer_lb","timer","tracker","tree_farmer_achieve","tree_poly_farmer","unlocks_analyze","unlocks_mapper","unlocks_mapper_out","weird_farmer","weird_multi_farmer","weird_multi_section","weird_section","smart_poly_farmer"],"openFilePositions":[{"key":"basic_plant_column","value":{"x":-1461.890869140625,"y":885.687744140625}},{"key":"cactus_brick_lb","value":{"x":-579.6218872070313,"y":1923.084228515625}},{"key":"cactus_farmer","value":{"x":-1313.192626953125,"y":1972.97265625}},{"key":"cactus_farmer_lb","value":{"x":-2466.314453125,"y":1902.706787109375}},{"key":"cactus_lb","value":{"x":-607.6986694335938,"y":1990.58935546875}},{"key":"cactus_section","value":{"x":-347.08294677734377,"y":147.863525390625}},{"key":"cactus_single_lb","value":{"x":-599.3749389648438,"y":1778.662109375}},{"key":"cactus_spam_lb","value":{"x":-616.1940307617188,"y":1832.1424560546875}},{"key":"calc_actual_costs","value":{"x":1398.6513671875,"y":-162.4632568359375}},{"key":"carrot_farmer_achiev","value":{"x":-1895.220458984375,"y":2248.00830078125}},{"key":"carrot_poly_farmer","value":{"x":-1277.223876953125,"y":1669.5521240234375}},{"key":"column_farmer","value":{"x":-1465.126953125,"y":978.6971435546875}},{"key":"common","value":{"x":-407.70965576171877,"y":607.072509765625}},{"key":"dinosaur_farmer","value":{"x":-1298.767333984375,"y":2063.7744140625}},{"key":"dinosaur_farmer_lb","value":{"x":-2464.1181640625,"y":1959.0347900390625}},{"key":"dinosaur_section","value":{"x":-1805.7705078125,"y":-2.190673828125}},{"key":"dumbflower_section","value":{"x":-1242.577392578125,"y":378.4588623046875}},{"key":"entity_item_mapping","value":{"x":-326.58551025390627,"y":-209.7154541015625}},{"key":"f0","value":{"x":-2715.245849609375,"y":112.595703125}},{"key":"f1","value":{"x":-2716.367431640625,"y":179.662841796875}},{"key":"f2","value":{"x":-103.25067138671875,"y":-529.8878173828125}},{"key":"f3","value":{"x":-66.99102783203125,"y":-636.4552001953125}},{"key":"fastest_lb","value":{"x":2959.782958984375,"y":336.788330078125}},{"key":"fastest_step_map","value":{"x":2936.829345703125,"y":1324.9755859375}},{"key":"flip_achieve","value":{"x":-537.1980590820313,"y":1534.8197021484375}},{"key":"hay_farmer_achieve","value":{"x":-564.8129272460938,"y":1650.451171875}},{"key":"hay_poly_farmer","value":{"x":-1277.788818359375,"y":1777.9263916015625}},{"key":"leaderboard","value":{"x":-2451.001708984375,"y":2261.72021484375}},{"key":"leaderboard_fastest","value":{"x":2885.281005859375,"y":2335.901611328125}},{"key":"main","value":{"x":-1301.457275390625,"y":2248.33544921875}},{"key":"maze_calc_farmer","value":{"x":-641.6542358398438,"y":2161.9921875}},{"key":"maze_farmer","value":{"x":-1286.78173828125,"y":1908.8336181640625}},{"key":"maze_farmer_lb","value":{"x":-2471.41796875,"y":2035.1845703125}},{"key":"maze_fill","value":{"x":-2710.380126953125,"y":712.9439697265625}},{"key":"maze_full_rand","value":{"x":-2720.871826171875,"y":632.697265625}},{"key":"maze_multi_a_star","value":{"x":-2705.802001953125,"y":556.5430908203125}},{"key":"maze_multi_dfs","value":{"x":-2717.973388671875,"y":772.414306640625}},{"key":"maze_multi_reuse","value":{"x":-2724.851318359375,"y":473.7208251953125}},{"key":"maze_pre_path","value":{"x":-2712.381103515625,"y":850.6080322265625}},{"key":"maze_reuse_analysis","value":{"x":-1341.393310546875,"y":219.74365234375}},{"key":"maze_reuse_section","value":{"x":-2729.575439453125,"y":405.3192138671875}},{"key":"maze_section","value":{"x":-2704.888916015625,"y":1029.157958984375}},{"key":"maze_section_a_star","value":{"x":-2716.437744140625,"y":940.3837890625}},{"key":"old_code","value":{"x":-252.33990478515626,"y":-419.4515380859375}},{"key":"point","value":{"x":-416.95440673828127,"y":942.10595703125}},{"key":"pumpkin_farmer_lb","value":{"x":-2481.488037109375,"y":2101.20703125}},{"key":"pumpkin_section","value":{"x":-364.11114501953127,"y":60.908447265625}},{"key":"rect","value":{"x":-415.78948974609377,"y":865.6341552734375}},{"key":"save_state","value":{"x":-333.51141357421877,"y":-289.3511962890625}},{"key":"suggester","value":{"x":-381.41717529296877,"y":-55.4696044921875}},{"key":"sunflower_column","value":{"x":-1237.1640625,"y":455.961669921875}},{"key":"sunflower_farmer","value":{"x":-1318.281982421875,"y":2162.34326171875}},{"key":"sunflower_farmer_lb","value":{"x":-2467.609130859375,"y":2179.0341796875}},{"key":"timer","value":{"x":-415.54583740234377,"y":690.2220458984375}},{"key":"tracker","value":{"x":-407.29144287109377,"y":789.34765625}},{"key":"tree_farmer_achieve","value":{"x":-1906.346923828125,"y":2165.01708984375}},{"key":"tree_poly_farmer","value":{"x":-1323.301513671875,"y":1518.9501953125}},{"key":"unlocks_analyze","value":{"x":-350.86236572265627,"y":331.7835693359375}},{"key":"unlocks_mapper","value":{"x":-393.01483154296877,"y":496.24560546875}},{"key":"unlocks_mapper_out","value":{"x":-395.95074462890627,"y":397.7666015625}},{"key":"weird_farmer","value":{"x":-626.0813598632813,"y":2072.42041015625}},{"key":"weird_multi_farmer","value":{"x":-644.6591186523438,"y":2245.95068359375}},{"key":"weird_multi_section","value":{"x":-1524.507080078125,"y":694.1973876953125}},{"key":"weird_section","value":{"x":-1497.51123046875,"y":782.9139404296875}},{"key":"docs0","value":{"x":-904.6360473632813,"y":3051.557373046875}},{"key":"docs1","value":{"x":-1987.820068359375,"y":3086.8193359375}},{"key":"docs3","value":{"x":2831.034912109375,"y":-805.207275390625}},{"key":"smart_poly_farmer","value":{"x":-2439.979736328125,"y":1746.322021484375}}],"openFileScrollPositions":[{"key":"basic_plant_column","value":23.6463623046875},{"key":"cactus_brick_lb","value":2372.087646484375},{"key":"cactus_farmer","value":150.00030517578126},{"key":"cactus_farmer_lb","value":0.0001220703125},{"key":"cactus_lb","value":199.99945068359376},{"key":"cactus_section","value":4492.31396484375},{"key":"cactus_single_lb","value":199.99972534179688},{"key":"cactus_spam_lb","value":-300.00079345703127},{"key":"calc_actual_costs","value":9413.7392578125},{"key":"carrot_farmer_achiev","value":-0.0009765625},{"key":"carrot_poly_farmer","value":1657.67578125},{"key":"column_farmer","value":99.9991455078125},{"key":"common","value":3974.030029296875},{"key":"dinosaur_farmer","value":0.0},{"key":"dinosaur_farmer_lb","value":50.0},{"key":"dinosaur_section","value":8699.962890625},{"key":"dumbflower_section","value":292.38543701171877},{"key":"entity_item_mapping","value":50.0008544921875},{"key":"f0","value":208.09173583984376},{"key":"f1","value":300.0817565917969},{"key":"f2","value":200.0},{"key":"f3","value":117.44920349121094},{"key":"fastest_lb","value":1455.6787109375},{"key":"fastest_step_map","value":-0.00042724609375},{"key":"flip_achieve","value":92.24417114257813},{"key":"hay_farmer_achieve","value":0.0},{"key":"hay_poly_farmer","value":-0.000732421875},{"key":"leaderboard","value":0.0},{"key":"leaderboard_fastest","value":0.0},{"key":"main","value":0.0},{"key":"maze_calc_farmer","value":2102.469482421875},{"key":"maze_farmer","value":100.0},{"key":"maze_farmer_lb","value":49.9998779296875},{"key":"maze_fill","value":2976.964111328125},{"key":"maze_full_rand","value":3286.147216796875},{"key":"maze_multi_a_star","value":2190.42578125},{"key":"maze_multi_dfs","value":2732.41650390625},{"key":"maze_multi_reuse","value":3386.07861328125},{"key":"maze_pre_path","value":5349.974609375},{"key":"maze_reuse_analysis","value":143.20872497558595},{"key":"maze_reuse_section","value":11537.126953125},{"key":"maze_section","value":779.94482421875},{"key":"maze_section_a_star","value":3779.693359375},{"key":"old_code","value":700.0},{"key":"point","value":150.00274658203126},{"key":"pumpkin_farmer_lb","value":0.0},{"key":"pumpkin_section","value":1402.93896484375},{"key":"rect","value":236.45733642578126},{"key":"save_state","value":812.6764526367188},{"key":"suggester","value":1399.970947265625},{"key":"sunflower_column","value":2069.3935546875},{"key":"sunflower_farmer","value":0.00048828125},{"key":"sunflower_farmer_lb","value":50.0},{"key":"timer","value":-49.999114990234378},{"key":"tracker","value":652.107421875},{"key":"tree_farmer_achieve","value":499.99896240234377},{"key":"tree_poly_farmer","value":541.565673828125},{"key":"unlocks_analyze","value":599.9658203125},{"key":"unlocks_mapper","value":-50.0009765625},{"key":"unlocks_mapper_out","value":0.000030517578125},{"key":"weird_farmer","value":0.001220703125},{"key":"weird_multi_farmer","value":0.0009765625},{"key":"weird_multi_section","value":1045.86376953125},{"key":"weird_section","value":1425.554443359375},{"key":"smart_poly_farmer","value":-0.0009765625}],"openFileSizes":[{"key":"basic_plant_column","value":{"x":0.0,"y":1131.6964111328125}},{"key":"cactus_brick_lb","value":{"x":1312.4906005859375,"y":718.762451171875}},{"key":"cactus_farmer","value":{"x":0.0,"y":711.674560546875}},{"key":"cactus_farmer_lb","value":{"x":1070.442626953125,"y":579.1139526367188}},{"key":"cactus_lb","value":{"x":1284.1839599609375,"y":845.6926879882813}},{"key":"cactus_section","value":{"x":0.0,"y":1105.6385498046875}},{"key":"cactus_single_lb","value":{"x":1013.4149780273438,"y":437.0865173339844}},{"key":"cactus_spam_lb","value":{"x":1096.0860595703125,"y":638.0873413085938}},{"key":"calc_actual_costs","value":{"x":0.0,"y":1179.0809326171875}},{"key":"carrot_farmer_achiev","value":{"x":1279.48681640625,"y":731.4683837890625}},{"key":"carrot_poly_farmer","value":{"x":1090.0323486328125,"y":602.6275634765625}},{"key":"column_farmer","value":{"x":1547.891845703125,"y":1200.7545166015625}},{"key":"common","value":{"x":1302.51708984375,"y":695.440185546875}},{"key":"dinosaur_farmer","value":{"x":834.8248901367188,"y":510.09942626953127}},{"key":"dinosaur_farmer_lb","value":{"x":1042.097900390625,"y":0.0}},{"key":"dinosaur_section","value":{"x":1461.9139404296875,"y":934.9783325195313}},{"key":"dumbflower_section","value":{"x":1289.2303466796875,"y":679.3845825195313}},{"key":"entity_item_mapping","value":{"x":1267.0860595703125,"y":804.102294921875}},{"key":"f0","value":{"x":1055.6260986328125,"y":605.8484497070313}},{"key":"f1","value":{"x":986.4697875976563,"y":527.9984741210938}},{"key":"f2","value":{"x":0.0,"y":506.1300048828125}},{"key":"f3","value":{"x":0.0,"y":517.2512817382813}},{"key":"fastest_lb","value":{"x":0.0,"y":1013.9221801757813}},{"key":"fastest_step_map","value":{"x":0.0,"y":687.959716796875}},{"key":"flip_achieve","value":{"x":744.0,"y":428.0}},{"key":"hay_farmer_achieve","value":{"x":1478.2562255859375,"y":618.974365234375}},{"key":"hay_poly_farmer","value":{"x":1301.30078125,"y":1265.944580078125}},{"key":"leaderboard","value":{"x":0.0,"y":290.0306396484375}},{"key":"leaderboard_fastest","value":{"x":1131.9300537109375,"y":823.784423828125}},{"key":"main","value":{"x":0.0,"y":943.2000732421875}},{"key":"maze_calc_farmer","value":{"x":0.0,"y":646.5505981445313}},{"key":"maze_farmer","value":{"x":1303.55322265625,"y":863.1484375}},{"key":"maze_farmer_lb","value":{"x":1107.1624755859375,"y":696.0368041992188}},{"key":"maze_fill","value":{"x":1216.429443359375,"y":748.2077026367188}},{"key":"maze_full_rand","value":{"x":1187.3421630859375,"y":661.6863403320313}},{"key":"maze_multi_a_star","value":{"x":1335.8546142578125,"y":1011.697021484375}},{"key":"maze_multi_dfs","value":{"x":0.0,"y":1396.169921875}},{"key":"maze_multi_reuse","value":{"x":0.0,"y":1057.4356689453125}},{"key":"maze_pre_path","value":{"x":0.0,"y":693.0254516601563}},{"key":"maze_reuse_analysis","value":{"x":1017.759033203125,"y":548.7219848632813}},{"key":"maze_reuse_section","value":{"x":0.0,"y":1030.1533203125}},{"key":"maze_section","value":{"x":1108.3505859375,"y":805.99267578125}},{"key":"maze_section_a_star","value":{"x":1174.9652099609375,"y":735.01171875}},{"key":"old_code","value":{"x":0.0,"y":0.0}},{"key":"point","value":{"x":1147.1319580078125,"y":668.5117797851563}},{"key":"pumpkin_farmer_lb","value":{"x":1232.515625,"y":615.3101196289063}},{"key":"pumpkin_section","value":{"x":1148.43603515625,"y":975.7649536132813}},{"key":"rect","value":{"x":0.0,"y":763.0130004882813}},{"key":"save_state","value":{"x":1456.642578125,"y":809.4170532226563}},{"key":"suggester","value":{"x":1076.5626220703125,"y":702.4791259765625}},{"key":"sunflower_column","value":{"x":1273.8079833984375,"y":1157.2215576171875}},{"key":"sunflower_farmer","value":{"x":980.4688110351563,"y":699.4562377929688}},{"key":"sunflower_farmer_lb","value":{"x":0.0,"y":0.0}},{"key":"timer","value":{"x":1082.6663818359375,"y":576.1023559570313}},{"key":"tracker","value":{"x":0.0,"y":676.3052978515625}},{"key":"tree_farmer_achieve","value":{"x":1621.0970458984375,"y":881.6611328125}},{"key":"tree_poly_farmer","value":{"x":1321.3603515625,"y":689.5951538085938}},{"key":"unlocks_analyze","value":{"x":1044.8358154296875,"y":873.3544311523438}},{"key":"unlocks_mapper","value":{"x":1037.7239990234375,"y":601.9619140625}},{"key":"unlocks_mapper_out","value":{"x":1041.717041015625,"y":563.363037109375}},{"key":"weird_farmer","value":{"x":1138.2020263671875,"y":667.0482177734375}},{"key":"weird_multi_farmer","value":{"x":1148.5963134765625,"y":433.69293212890627}},{"key":"weird_multi_section","value":{"x":1451.7532958984375,"y":1142.2452392578125}},{"key":"weird_section","value":{"x":1065.1280517578125,"y":712.5127563476563}},{"key":"docs0","value":{"x":900.0,"y":700.0}},{"key":"docs1","value":{"x":900.0,"y":700.0}},{"key":"docs3","value":{"x":1009.8460083007813,"y":700.0}},{"key":"smart_poly_farmer","value":{"x":1150.64599609375,"y":681.5425415039063}}],"openDocPages":[{"key":"docs0","value":"docs/unlocks/leaderboard.md"},{"key":"docs1","value":"docs/unlocks/dinosaurs.md"},{"key":"docs3","value":"docs/output.md"}],"unlocks":["grass_10","soil","harvest","pass","do_a_flip","pet_the_piggy","grassland","hay","straw_hat","while","true","false","break","continue","loops","speed_5","can_harvest","if","else","elif","change_hat","gray_hat","purple_hat","green_hat","brown_hat","hats","expand_9","move","north","south","east","west","for","range","get_world_size","wood","bush","entities","clear","plant","print","quick_print","unlocks","str","debug","and","or","not","operators","carrots_10","carrot","till","can_trade","trade","items","carrot_seed","get_entity_type","get_ground_type","grounds","get_pos_x","get_pos_y","none","num_items","num_unlocked","senses","watering_9","water","use_item","get_water","traffic_cone","variables","functions","def","return","global","tree_hat","append","remove","pop","insert","len","list","lists","carrot_hat","trees_10","tree","from","import","sunflower_seed","sunflower","power","get_active_power","measure","sunflowers","pumpkin","pumpkin_seed","dead_pumpkin","pumpkins_10","pumpkin_hat","dicts","sets","add","dict","set","dictionaries","wizard_hat","sunflower_hat","get_cost","costs","min","max","abs","random","utilities","weird_substance","fertilizer_4","get_companion","polyculture_5","cactus_6","swap","cactus_seed","get_time","get_tick_count","timing","cactus_hat","unlock","auto_unlock","dinosaur","egg","bone","dinosaur_hat","apple","can_move","dinosaurs_6","mazes_6","hedge","treasure","gold","gold_hat","megafarm_5","get_drone_id","num_drones","max_drones","wait_for","spawn_drone","has_finished","simulate","simulation","set_execution_speed","set_world_size","debug_2","golden_sunflower_hat","the_farmers_remains","top_hat","leaderboard_run","leaderboards","leaderboard","golden_gold_hat","golden_cactus_hat","traffic_cone_stack","golden_pumpkin_hat"],"version":3}